cloudmesh_google-4.1.9-py3.8-nspkg.pth
cloudmesh/google/__init__.py
cloudmesh/google/__version__.py
cloudmesh/google/command/__init__.py
cloudmesh/google/command/google.py
cloudmesh/google/googlebigquery/Provider.py
cloudmesh/google/googlebigquery/Provider_con_test.py
cloudmesh/google/googlebigquery/__init__.py
cloudmesh/google/googlebigquery/__version__.py
cloudmesh/google/googlebigquery/api/__init__.py
cloudmesh/google/googlebigquery/api/manager.py
cloudmesh/google/googlebigquery/command/__init__.py
cloudmesh/google/googlebigquery/command/googlebigquery.py
cloudmesh/google/storage/Provider.py
cloudmesh/google/storage/__init__.py
cloudmesh_google-4.1.9.dist-info/LICENSE
cloudmesh_google-4.1.9.dist-info/METADATA
cloudmesh_google-4.1.9.dist-info/WHEEL
cloudmesh_google-4.1.9.dist-info/namespace_packages.txt
cloudmesh_google-4.1.9.dist-info/top_level.txt
cloudmesh_google-4.1.9.dist-info/RECORD
